Workbook

Sheet Assumptions
A1: Google Resume Studio — GTM Model Assumptions
A2: Blue cells = hardcoded inputs (edit these). Black = formulas. Yellow fill = key levers.
A4: Assumption | B4: Value | C4: Source / rationale
A5: Free → paid conversion (of signups) | B5: 0.03 | C5: Freemium median 2–5% (knowledgelib.io 2026); consumer 1–3%
A6: Monthly paid churn | B6: 0.07 | C6: Job-search tools churn high; ~30% of annual subs cancel in month 1 (RevenueCat 2025). Annual-plan mix pulls blended churn to 7%
A7: Blended ARPU / month | B7: 7.99 | C7: Mix of $9.99/mo and $59.99/yr plans
A8: Monthly plan price | B8: 9.99 | C8: 1/3 of Zety ($25.95/4wk), Teal ($29), Rezi ($29)
A9: Annual plan price | B9: 59.99 | C9: 50% effective discount to shift mix to annual
A10: Gross margin | B10: 0.85 | C10: Consumer SaaS typical; includes inference cost
A11: Activation rate (resume completed + exported) | B11: 0.55 | C11: Consumer tool benchmark 40–60%
A12: Year-1 S&M budget | B12: 12000000 | C12: See Budget sheet

Sheet Monthly Model
A1: Year-1 Monthly Model (launch = Month 1)
A3: Line | B3: M1 | C3: M2 | D3: M3 | E3: M4 | F3: M5 | G3: M6 | H3: M7 | I3: M8 | J3: M9 | K3: M10 | L3: M11 | M3: M12 | N3: Year 1
A4: New signups (input) | B4: 200000 | C4: 300000 | D4: 400000 | E4: 450000 | F4: 500000 | G4: 550000 | H4: 550000 | I4: 500000 | J4: 550000 | K4: 650000 | L4: 700000 | M4: 650000 | N4: =SUM(B4:M4) -> 6000000
A5: Activated users | B5: =B4*Assumptions!$B$11 -> 110000 | C5: =C4*Assumptions!$B$11 -> 165000 | D5: =D4*Assumptions!$B$11 -> 220000 | E5: =E4*Assumptions!$B$11 -> 247500 | F5: =F4*Assumptions!$B$11 -> 275000 | G5: =G4*Assumptions!$B$11 -> 302500 | H5: =H4*Assumptions!$B$11 -> 302500 | I5: =I4*Assumptions!$B$11 -> 275000 | ... M5: =M4*Assumptions!$B$11 -> 357500 | N5: =SUM(B5:M5) -> 3300000
A6: New paying subscribers | B6: =B4*Assumptions!$B$5 -> 6000 | C6: =C4*Assumptions!$B$5 -> 9000 | D6: =D4*Assumptions!$B$5 -> 12000 | E6: =E4*Assumptions!$B$5 -> 13500 | F6: =F4*Assumptions!$B$5 -> 15000 | G6: =G4*Assumptions!$B$5 -> 16500 | H6: =H4*Assumptions!$B$5 -> 16500 | I6: =I4*Assumptions!$B$5 -> 15000 | ... M6: =M4*Assumptions!$B$5 -> 19500 | N6: =SUM(B6:M6) -> 180000
A7: Churned subscribers | B7: 0 | C7: =B8*Assumptions!$B$6 -> 420 | D7: =C8*Assumptions!$B$6 -> 1020.6 | E7: =D8*Assumptions!$B$6 -> 1789.158 | F7: =E8*Assumptions!$B$6 -> 2608.9169 | G7: =F8*Assumptions!$B$6 -> 3476.2928 | H7: =G8*Assumptions!$B$6 -> 4387.9523 | I7: =H8*Assumptions!$B$6 -> 5235.7956 | J7: =I8*Assumptions!$B$6 -> 5919.2899 | ... M7: =L8*Assumptions!$B$6 -> 8499.6318 | N7: =SUM(B7:M7) -> 47576.321
A8: Ending paying subscribers | B8: =B6 -> 6000 | C8: =B8-C7+C6 -> 14580 | D8: =C8-D7+D6 -> 25559.4 | E8: =D8-E7+E6 -> 37270.242 | F8: =E8-F7+F6 -> 49661.325 | G8: =F8-G7+G6 -> 62685.032 | H8: =G8-H7+H6 -> 74797.08 | I8: =H8-I7+I6 -> 84561.284 | J8: =I8-J7+J6 -> 95141.995 | ... M8: =L8-M7+M6 -> 132423.68 | N8: =M8 -> 132423.68
A9: MRR | B9: =B8*Assumptions!$B$7 -> 47940 | C9: =C8*Assumptions!$B$7 -> 116494.2 | D9: =D8*Assumptions!$B$7 -> 204219.61 | E9: =E8*Assumptions!$B$7 -> 297789.23 | F9: =F8*Assumptions!$B$7 -> 396793.99 | G9: =G8*Assumptions!$B$7 -> 500853.41 | H9: =H8*Assumptions!$B$7 -> 597628.67 | I9: =I8*Assumptions!$B$7 -> 675644.66 | ... M9: =M8*Assumptions!$B$7 -> 1058065.2 | N9: =M9 -> 1058065.2
A10: Revenue (monthly) | B10: =B9 -> 47940 | C10: =C9 -> 116494.2 | D10: =D9 -> 204219.61 | E10: =E9 -> 297789.23 | F10: =F9 -> 396793.99 | G10: =G9 -> 500853.41 | H10: =H9 -> 597628.67 | I10: =I9 -> 675644.66 | ... M10: =M9 -> 1058065.2 | N10: =SUM(B10:M10) -> 6488562.4
A11: Gross profit | B11: =B10*Assumptions!$B$10 -> 40749 | C11: =C10*Assumptions!$B$10 -> 99020.07 | D11: =D10*Assumptions!$B$10 -> 173586.67 | E11: =E10*Assumptions!$B$10 -> 253120.85 | F11: =F10*Assumptions!$B$10 -> 337274.89 | G11: =G10*Assumptions!$B$10 -> 425725.4 | H11: =H10*Assumptions!$B$10 -> 507984.37 | I11: =I10*Assumptions!$B$10 -> 574297.96 | ... M11: =M10*Assumptions!$B$10 -> 899355.42 | N11: =SUM(B11:M11) -> 5515278
A13: Note: signup ramp (blue) reflects launch spike, summer dip (M7–M8), and September/January hiring surges. All other rows are formulas driven by the Assumptions sheet.

Sheet KPI Dashboard
A1: KPI Dashboard — Year-1 Targets vs Model
A3: KPI | B3: Model output | C3: Target | D3: Status | E3: Benchmark / definition
A4: Total signups | B4: ='Monthly Model'!N4 -> 6000000 | C4: 6000000 | D4: =IF(B4>=C4,"On track","Below target") -> On track | E4: New free accounts, 12 months
A5: Activation rate | B5: =Assumptions!B11 -> 0.55 | C5: 0.55 | D5: =IF(B5>=C5,"On track","Below target") -> On track | E5: Completed + exported a resume (benchmark 40–60%)
A6: Free → paid conversion | B6: =Assumptions!B5 -> 0.03 | C6: 0.03 | D6: =IF(B6>=C6,"On track","Below target") -> On track | E6: Freemium median 2–5%
A7: Paying subscribers acquired | B7: ='Monthly Model'!N6 -> 180000 | C7: 180000 | D7: =IF(B7>=C7,"On track","Below target") -> On track | E7: Cumulative new payers
A8: Ending paying subscribers | B8: ='Monthly Model'!N8 -> 132423.68 | C8: 130000 | D8: =IF(B8>=C8,"On track","Below target") -> On track | E8: After churn, month 12
A9: Year-1 revenue | B9: ='Monthly Model'!N10 -> 6488562.4 | C9: 6000000 | D9: =IF(B9>=C9,"On track","Below target") -> On track | E9: Subscription revenue
A10: Exit ARR | B10: ='Monthly Model'!M9*12 -> 12696782 | C10: 12000000 | D10: =IF(B10>=C10,"On track","Below target") -> On track | E10: Month-12 MRR × 12
A11: Blended CAC (per payer) | B11: =Assumptions!B12/'Monthly Model'!N6 -> 66.666667 | C11: 70 | D11: =IF(B11<=C11,"On track","Above target") -> On track | E11: Total S&M ÷ payers acquired; consumer benchmark $20–80
A12: CAC per signup | B12: =Assumptions!B12/'Monthly Model'!N4 -> 2 | C12: 2.5 | D12: =IF(B12<=C12,"On track","Above target") -> On track | E12: Total S&M ÷ signups
A13: LTV (contribution) | B13: =Assumptions!B7/Assumptions!B6*Assumptions!B10 -> 97.021429 | C13: 90 | D13: =IF(B13>=C13,"On track","Below target") -> On track | E13: ARPU ÷ churn × gross margin
A14: LTV : CAC (launch year) | B14: =B13/B11 -> 1.4553214 | C14: 1.3 | D14: =IF(B14>=C14,"On track","Below target") -> On track | E14: Incl. one-time brand spend; steady-state ~3.2x at $30 CAC
A15: Monthly paid churn | B15: =Assumptions!B6 -> 0.07 | C15: 0.07 | D15: =IF(B15<=C15,"On track","Above target") -> On track | E15: Logo churn; annual mix reduces blended churn
A17: North star metric: tailored resumes delivered per week — target 1M/week by month 12 (tracked in product analytics, not modeled here).
A18: Kill criteria: if conversion <1.5% or D30 retention <15% at month 6, pause paid spend and fix product.

Sheet Budget
A1: Year-1 Launch Budget — $12M
A3: Line item | B3: Amount | C3: % of total | D3: Notes
A4: Paid media (Search, YouTube, social) | B4: 5000000 | C4: =B4/$B$10 -> 0.41666667 | D4: Weighted to launch quarter + January surge
A5: Brand & launch moment | B5: 2500000 | C5: =B5/$B$10 -> 0.20833333 | D5: Launch film, keynote assets, OOH in 5 metros
A6: Creator & influencer program | B6: 1500000 | C6: =B6/$B$10 -> 0.125 | D6: 50 career creators, always-on
A7: Partnerships & campus | B7: 1200000 | C7: =B7/$B$10 -> 0.1 | D7: 200 university career centers, workforce orgs
A8: PR, data reports, events | B8: 800000 | C8: =B8/$B$10 -> 0.066666667 | D8: Two agencies + quarterly Job Search Trends reports
A9: Research, measurement, creative ops | B9: 1000000 | C9: =B9/$B$10 -> 0.083333333 | D9: Brand-lift, MMM, localization
A10: Total | B10: =SUM(B4:B9) -> 12000000 | C10: =B10/B10 -> 1 | D10: Must equal Assumptions!B12
